hwpx_mcp_server/__init__.py
hwpx_mcp_server/hwpx_ops.py
hwpx_mcp_server/logging_conf.py
hwpx_mcp_server/server.py
hwpx_mcp_server/storage.py
hwpx_mcp_server/tools.py
hwpx_mcp_server/core/context.py
hwpx_mcp_server/core/diff.py
hwpx_mcp_server/core/handles.py
hwpx_mcp_server/core/locator.py
hwpx_mcp_server/core/plan.py
hwpx_mcp_server/core/txn.py
hwpx_mcp_server/metadata/tools_meta.py
hwpx_mcp_server/schema/builder.py
hwpx_mcp_server/schema/sanitizer.py
hwpx_mcp_server-0.5.0.dist-info/licenses/LICENSE
hwpx_mcp_server-0.5.0.dist-info/METADATA
hwpx_mcp_server-0.5.0.dist-info/WHEEL
hwpx_mcp_server-0.5.0.dist-info/entry_points.txt
hwpx_mcp_server-0.5.0.dist-info/top_level.txt
hwpx_mcp_server-0.5.0.dist-info/RECORD
