Metadata-Version: 2.4
Name: hwpx-mcp-server
Version: 0.5.0
Summary: Model Context Protocol server for local HWPX document automation.
Author: Kohkyuhyun
License: MIT License
Requires-Python: >=3.10
License-File: LICENSE
Requires-Dist: python-hwpx>=1.9
Requires-Dist: pydantic>=2.7
Requires-Dist: anyio>=4.0
Requires-Dist: mcp>=1.14.1
Requires-Dist: modelcontextprotocol>=0.1.0
Provides-Extra: test
Requires-Dist: pytest>=8.0; extra == "test"
Dynamic: license-file
